{
  "$schema": "https://json-schema.org/draft/2020-12/schema",
  "$id": "https://gocell.dev/schemas/contract.schema.json",
  "title": "GoCell Contract Descriptor",
  "description": "Defines a Contract, the cross-Cell boundary protocol. All interactions between L1+ Cells require a contract. The endpoints structure varies by kind (http, event, command, projection).",
  "type": "object",
  "required": ["id", "kind", "consistencyLevel", "lifecycle", "endpoints"],
  "additionalProperties": false,
  "properties": {
    "id": {
      "type": "string",
      "description": "Unique contract identifier in the form {kind}.{domain-path}.{version}.",
      "pattern": "^(http|event|command|projection)\\..+\\.v[0-9]+$"
    },
    "kind": {
      "type": "string",
      "description": "Contract kind that determines the endpoint structure.",
      "enum": ["http", "event", "command", "projection"]
    },
    "ownerCell": {
      "type": "string",
      "description": "The cell that owns (provides) this contract. Defaults to the provider endpoint cell. May be omitted."
    },
    "consistencyLevel": {
      "type": "string",
      "description": "Consistency level for this contract. Must not exceed the provider cell's consistency level.",
      "enum": ["L0", "L1", "L2", "L3", "L4"]
    },
    "lifecycle": {
      "type": "string",
      "description": "Lifecycle stage. Transitions are one-way: draft -> active -> deprecated.",
      "enum": ["draft", "active", "deprecated"]
    },
    "endpoints": {
      "type": "object",
      "description": "Provider and consumer endpoints. Structure depends on the contract kind."
    },
    "schemaRefs": {
      "type": "object",
      "description": "References to JSON Schema files for request/response or payload validation. Paths are relative to the contract.yaml directory.",
      "additionalProperties": {
        "type": "string"
      }
    },
    "replayable": {
      "type": "boolean",
      "description": "Whether the event or projection supports replay. Required for kind=event and kind=projection."
    },
    "idempotencyKey": {
      "type": "string",
      "description": "Field used as the idempotency key. Required for kind=event."
    },
    "deliverySemantics": {
      "type": "string",
      "description": "Delivery guarantee. Required for kind=event.",
      "enum": ["at-least-once", "exactly-once"]
    },
    "codegen": {
      "type": "boolean",
      "default": false,
      "description": "Opt the contract into `gocell generate contract` output. When true, contractgen produces types_gen.go / iface_gen.go (and handler_gen.go for kind=http). Default false; will be removed in PR-4 when all contracts are migrated."
    },
    "description": {
      "type": "string",
      "description": "Human-readable description of the contract's purpose."
    },
    "deprecatedAt": {
      "type": "string",
      "format": "date",
      "pattern": "^[0-9]{4}-[0-9]{2}-[0-9]{2}$",
      "description": "Date the contract entered the deprecated lifecycle stage (YYYY-MM-DD). Required when lifecycle=deprecated. Enforced by FMT-23."
    }
  },
  "$defs": {
    "paramSchema": {
      "type": "object",
      "required": ["type"],
      "additionalProperties": false,
      "properties": {
        "type": {
          "type": "string",
          "enum": ["string", "integer", "number", "boolean"],
          "description": "Primitive type of the parameter. UUID parameters use type=string with format=uuid."
        },
        "required": {
          "type": "boolean",
          "description": "Whether the parameter is required. Omitted for path params (always required); default false for query params."
        },
        "format": {
          "type": "string",
          "description": "Optional format hint (e.g. uuid, date-time, int64)."
        },
        "minLength": {
          "type": "integer",
          "minimum": 0,
          "description": "Minimum string length accepted for this parameter. Required by FMT-25 for non-uuid string path/query params."
        },
        "maxLength": {
          "type": "integer",
          "minimum": 0,
          "description": "Maximum string length accepted for this parameter. Required by FMT-25 for non-uuid string path/query params."
        },
        "minimum": {
          "type": "integer",
          "description": "Minimum numeric value accepted for this parameter. Required by FMT-25 for integer and number path/query params."
        },
        "maximum": {
          "type": "integer",
          "description": "Maximum numeric value accepted for this parameter. Required by FMT-25 for integer and number path/query params."
        }
      }
    }
  },
  "allOf": [
    {
      "if": {
        "properties": { "kind": { "const": "http" } },
        "required": ["kind"]
      },
      "then": {
        "properties": {
          "endpoints": {
            "type": "object",
            "required": ["server", "clients"],
            "additionalProperties": false,
            "properties": {
              "server": {
                "type": "string",
                "description": "The cell or actor that serves this HTTP endpoint."
              },
              "clients": {
                "type": "array",
                "description": "Cells or actors that call this HTTP endpoint.",
                "items": { "type": "string" }
              },
              "http": {
                "type": "object",
                "description": "Transport metadata elevating method, path, parameters, and status semantics to first-class contract fields.",
                "required": ["method", "path", "successStatus", "noContent"],
                "additionalProperties": false,
                "properties": {
                  "method": {
                    "type": "string",
                    "enum": ["GET", "POST", "PUT", "PATCH", "DELETE"],
                    "description": "HTTP method served by this contract."
                  },
                  "path": {
                    "type": "string",
                    "pattern": "^/",
                    "description": "HTTP path template served by this contract."
                  },
                  "pathParams": {
                    "type": "object",
                    "description": "Typed declarations for placeholders in the path template. Keys must match every {name} in path (FMT-13).",
                    "additionalProperties": {"$ref": "#/$defs/paramSchema"}
                  },
                  "queryParams": {
                    "type": "object",
                    "description": "Typed declarations for query string parameters accepted by this endpoint.",
                    "additionalProperties": {"$ref": "#/$defs/paramSchema"}
                  },
                  "successStatus": {
                    "type": "integer",
                    "minimum": 200,
                    "maximum": 299,
                    "description": "Expected success status for provider-driven verification."
                  },
                  "noContent": {
                    "type": "boolean",
                    "description": "Whether the success response must be bodyless."
                  },
                  "responses": {
                    "type": "object",
                    "description": "Optional map of HTTP error responses, keyed by status code. Value references a JSON Schema describing the error body.",
                    "patternProperties": {
                      "^[1-5][0-9][0-9]$": {
                        "type": "object",
                        "required": ["description", "schemaRef"],
                        "additionalProperties": false,
                        "properties": {
                          "description": {"type": "string"},
                          "schemaRef": {"type": "string"}
                        }
                      }
                    },
                    "additionalProperties": false
                  },
                  "auth": {
                    "type": "object",
                    "description": "Route-level authentication overrides for contractgen. Omit for standard authenticated routes.",
                    "additionalProperties": false,
                    "properties": {
                      "public": {
                        "type": "boolean",
                        "description": "If true, route is mounted as public (no JWT required). auth.Route{Public: true} is emitted by RegisterRoutes. Mutually exclusive with passwordResetExempt and bootstrap."
                      },
                      "passwordResetExempt": {
                        "type": "boolean",
                        "description": "If true, route bypasses the force-password-reset gate. auth.Route{PasswordResetExempt: true} is emitted. Mutually exclusive with public and bootstrap."
                      },
                      "bootstrap": {
                        "type": "boolean",
                        "description": "If true, contractgen generates a NewHandler(bootstrapAuth func(http.Handler) http.Handler, ...) constructor and emits auth.Route{BootstrapAuth: bootstrapAuth} from RegisterRoutes; the listener-level JWT middleware skips this route. Composition root injects the bootstrap Basic Auth + per-IP rate-limit middleware (GOCELL_BOOTSTRAP_ADMIN_USERNAME/PASSWORD env credentials). Mutually exclusive with public and passwordResetExempt. FMT-28 limits to setup/admin paths."
                      },
                      "responses": {
                        "type": "array",
                        "description": "HTTP status codes injected by listener-mounted middleware (e.g. bootstrap auth 401, rate limiter 429). CH-04 governance treats these as declared without requiring handler AST emission.",
                        "uniqueItems": true,
                        "items": {
                          "type": "integer",
                          "minimum": 100,
                          "maximum": 599
                        }
                      }
                    },
                    "allOf": [
                      {"not": {"required": ["public", "bootstrap"]}, "description": "auth.public and auth.bootstrap are mutually exclusive."},
                      {"not": {"required": ["public", "passwordResetExempt"]}, "description": "auth.public and auth.passwordResetExempt are mutually exclusive."},
                      {"not": {"required": ["bootstrap", "passwordResetExempt"]}, "description": "auth.bootstrap and auth.passwordResetExempt are mutually exclusive."}
                    ]
                  }
                }
              }
            }
          }
        }
      }
    },
    {
      "if": {
        "properties": { "kind": { "const": "event" } },
        "required": ["kind"]
      },
      "then": {
        "required": ["replayable", "idempotencyKey", "deliverySemantics"],
        "properties": {
          "endpoints": {
            "type": "object",
            "required": ["publisher", "subscribers"],
            "additionalProperties": false,
            "properties": {
              "publisher": {
                "type": "string",
                "description": "The cell that publishes this event."
              },
              "subscribers": {
                "type": "array",
                "description": "Cells or actors that subscribe to this event.",
                "items": { "type": "string" }
              }
            }
          }
        }
      }
    },
    {
      "if": {
        "properties": { "kind": { "const": "command" } },
        "required": ["kind"]
      },
      "then": {
        "properties": {
          "endpoints": {
            "type": "object",
            "required": ["handler", "invokers"],
            "additionalProperties": false,
            "properties": {
              "handler": {
                "type": "string",
                "description": "The cell that handles this command."
              },
              "invokers": {
                "type": "array",
                "description": "Cells or actors that invoke this command.",
                "items": { "type": "string" }
              }
            }
          }
        }
      }
    },
    {
      "if": {
        "properties": { "kind": { "const": "projection" } },
        "required": ["kind"]
      },
      "then": {
        "required": ["replayable"],
        "properties": {
          "endpoints": {
            "type": "object",
            "required": ["provider", "readers"],
            "additionalProperties": false,
            "properties": {
              "provider": {
                "type": "string",
                "description": "The cell that provides this projection."
              },
              "readers": {
                "type": "array",
                "description": "Cells or actors that read this projection.",
                "items": { "type": "string" }
              }
            }
          }
        }
      }
    }
  ]
}
